sobjanta_api_package/__init__.py
sobjanta_api_package/api_client.py
sobjanta_api_package-0.23.dist-info/METADATA
sobjanta_api_package-0.23.dist-info/WHEEL
sobjanta_api_package-0.23.dist-info/top_level.txt
sobjanta_api_package-0.23.dist-info/RECORD
