Metadata-Version: 2.1
Name: sobjanta_api_package
Version: 0.23
Summary: A Python client for interacting with a specific API.
Author: Imran Nur
Author-email: imrannur@techknowgram.com
Classifier: Programming Language :: Python :: 3
Classifier: License :: OSI Approved :: MIT License
Classifier: Operating System :: OS Independent
Requires-Python: >=3.6
Requires-Dist: requests
